[
    {
        "search_link": "https://twitter.com/search?q=%23hdfcloan&src=typed_query&f=top",
        "user_name": "Bhupesh",
        "user_handle": "/Bhupeshse",
        "tweet_date": "Jul 12",
        "timestamp": "2023-07-12T15:22:41.000Z",
        "tweet_content": "   #HDFCLoan    #CustomerComplaint  Again your representative is not allowing online prepayment quoting some annual limit.",
        "replies": "2",
        "retweets": "1",
        "likes": "",
        "app": "hdfc"
    },
    {
        "search_link": "https://twitter.com/search?q=%23hdfcloan&src=typed_query&f=top",
        "user_name": "Nitin Patil",
        "user_handle": "/nitin_patil28",
        "tweet_date": "Feb 4, 2021",
        "timestamp": "2021-02-04T17:51:48.000Z",
        "tweet_content": "Hey congratulations  , you are not alone harassing me.. just now now I came to know from your representative that   is also partner in the crime.. How   is making way of loot for u is very much evident..\n  #HDFCLoan   account no.-631872477/632277708",
        "replies": "1",
        "retweets": "1",
        "likes": "1",
        "app": "hdfc"
    },
    null,
    {
        "search_link": "https://twitter.com/search?q=%23hdfcloan&src=typed_query&f=top",
        "user_name": "tanka",
        "user_handle": "/TankaGajurrl",
        "tweet_date": "Jun 24, 2020",
        "timestamp": "2020-06-24T04:59:50.000Z",
        "tweet_content": "Dear   I m trying to take loan but not showing anything why ?\n        #HDFCLOAN",
        "replies": "2",
        "retweets": "",
        "likes": "",
        "app": "hdfc"
    },
    {
        "search_link": "https://twitter.com/search?q=%23hdfcloan&src=typed_query&f=top",
        "user_name": "Iam_Samirro",
        "user_handle": "/samirrout4455",
        "tweet_date": "Jun 27, 2021",
        "timestamp": "2021-06-27T15:19:32.000Z",
        "tweet_content": "I already send a mail regarding Fraud       But the problem still not resolved. Getting mentally  Harassed   || \n  #Hdfcloan    #rbipolicy   #loanfraud \n   #CORRUPTION   #Odisha   #Kendrapada   #MaskUpOdisha   #MaskUpIndia",
        "replies": "2",
        "retweets": "",
        "likes": "1",
        "app": "hdfc"
    },
    {
        "search_link": "https://twitter.com/search?q=%23hdfcloan&src=typed_query&f=top",
        "user_name": "MISSING MSD",
        "user_handle": "/MnsRaja19",
        "tweet_date": "Sep 25, 2022",
        "timestamp": "2022-09-25T05:09:26.000Z",
        "tweet_content": " worst loan section..and the most fraud cheater agents ......promised  the loan with rate of interst 9...but given as 10....term months 180.....after 10 months of deduction ..now it becomes 201 months term balance and 11.15 rate of interest.....  #hdfcloan",
        "replies": "3",
        "retweets": "",
        "likes": "",
        "app": "hdfc"
    },
    {
        "search_link": "https://twitter.com/search?q=%23hdfcloan&src=typed_query&f=top",
        "user_name": "iPlanet",
        "user_handle": "/iPlanetOfficial",
        "tweet_date": "May 12",
        "timestamp": "2023-05-12T10:59:39.000Z",
        "tweet_content": "iPad 10th gen - a thoughtful gift to amaze your mom! Zero-Interest 24-month EMI starts at just ₹1871*/month on HDFC  #ConsumerLoans  or  #BajajFinserv .\n\n #ipadpro   #mothersday   #mothersdaygift   #ipad10thgeneration    #HDFCLoan    #EMI   #BajajFinance   #NoCostEMI   #iPlanet",
        "replies": "",
        "retweets": "",
        "likes": "1",
        "app": "hdfc"
    },
    {
        "search_link": "https://twitter.com/search?q=%23hdfcloan&src=typed_query&f=top",
        "user_name": "gaurav rustagi",
        "user_handle": "/gaurav45678",
        "tweet_date": "Jun 3, 2020",
        "timestamp": "2020-06-03T07:01:19.000Z",
        "tweet_content": "pls upload link for ext. the moratorium from Jun to Aug\"The link will provided here shortly\" is displayed till now Note:The EMI payments in the month of Jun 2020 will be processed on the due dates as per standard process. why?\n  #hdfcmoratorium   #hdfccares   #hdfcbank    #hdfcloan",
        "replies": "1",
        "retweets": "",
        "likes": "",
        "app": "hdfc"
    },
    {
        "search_link": "https://twitter.com/search?q=%23hdfcloan&src=typed_query&f=top",
        "user_name": "Prabhu Natarajan",
        "user_handle": "/PrForexTrader",
        "tweet_date": "Jun 10, 2020",
        "timestamp": "2020-06-10T11:03:51.000Z",
        "tweet_content": "#hdfcbank    #HDFCLoan   Bank announced moratorium and still you took the money from my bank account.\nThe loan due was 5th and why did the bank took on 10th ?\nconsequence, Going to change the loan to Another bank and the other consequence, Close all my account with HDFC.",
        "replies": "1",
        "retweets": "",
        "likes": "1",
        "app": "hdfc"
    },
    {
        "search_link": "https://twitter.com/search?q=%23hdfcloan&src=typed_query&f=top",
        "user_name": "SmritiPSrivastava",
        "user_handle": "/smritiprasad07",
        "tweet_date": "Mar 5, 2022",
        "timestamp": "2022-03-05T08:01:06.000Z",
        "tweet_content": "To all spam call makers… how have you got my number when I do not consent for the same?   #hdfcloan    #ICICIBank   #axisbank   #banksinindia   #trai   #consumerprotection   #consumerforum",
        "replies": "1",
        "retweets": "",
        "likes": "",
        "app": "hdfc"
    },
    {
        "search_link": "https://twitter.com/search?q=%23hdfcloan&src=typed_query&f=top",
        "user_name": "Satish Singh",
        "user_handle": "/satish_sin",
        "tweet_date": "May 1",
        "timestamp": "2023-04-30T20:19:30.000Z",
        "tweet_content": "I am mentally harassed by loan recovery people and   #HDFCloan     where I have upfrontly told them that due to finance issues I will not be able to pay your rest of the amount. Please stop or I will do  #suiside",
        "replies": "1",
        "retweets": "2",
        "likes": "",
        "app": "hdfc"
    },
    {
        "search_link": "https://twitter.com/search?q=%23hdfcloan&src=typed_query&f=top",
        "user_name": "Nishant chandel",
        "user_handle": "/Nishantnc7",
        "tweet_date": "Dec 8, 2022",
        "timestamp": "2022-12-08T09:11:49.000Z",
        "tweet_content": "DEAR HDFC,\nKindly revert ASAP as it is urgent to pay the due amount .\n   \n #hdfc   #hdfcbank    #hdfcloan",
        "replies": "2",
        "retweets": "1",
        "likes": "",
        "app": "hdfc"
    },
    {
        "search_link": "https://twitter.com/search?q=%23hdfcloan&src=typed_query&f=top",
        "user_name": "Sandeep Mishr",
        "user_handle": "/sandeepsebol",
        "tweet_date": "May 17, 2021",
        "timestamp": "2021-05-17T03:44:59.000Z",
        "tweet_content": ",  #ShashidharJagdishan  sir, looking for some intervention -   #hdfcloan   is asking for int payments for a house they are yet to pay  #tridhatumorya  who has not done any constr citing  #covid . Do we have to pay for something that is bank and builders lapse ? ",
        "replies": "",
        "retweets": "",
        "likes": "",
        "app": "hdfc"
    },
    {
        "search_link": "https://twitter.com/search?q=%23hdfcloan&src=typed_query&f=top",
        "user_name": "sachbole",
        "user_handle": "/shykot",
        "tweet_date": "Oct 12, 2022",
        "timestamp": "2022-10-12T12:13:20.000Z",
        "tweet_content": "I only believe   #Hdfcloan   as a soul mate. They will keep calling for loan even if you are hospitalised.",
        "replies": "",
        "retweets": "",
        "likes": "",
        "app": "hdfc"
    },
    {
        "search_link": "https://twitter.com/search?q=%23hdfcloan&src=typed_query&f=top",
        "user_name": "Rajni Devi",
        "user_handle": "/RAJNIDE32013336",
        "tweet_date": "Nov 29, 2021",
        "timestamp": "2021-11-29T02:38:07.000Z",
        "tweet_content": "Thanks CSC for providing this facilities at Rural areas \nCar Loan Done Happy customer\nFor loan Just visit our CSC center\n\n #carloan    #hdfcloan    #loan   #carloan   #vehicleloan   #personalloan   #bikeloan   #agricultureloan   #hdfcbank",
        "replies": "2",
        "retweets": "",
        "likes": "2",
        "app": "hdfc"
    },
    {
        "search_link": "https://twitter.com/search?q=%23hdfcloan&src=typed_query&f=top",
        "user_name": "Vaibhav",
        "user_handle": "/Vaibhav69357983",
        "tweet_date": "May 28, 2020",
        "timestamp": "2020-05-28T06:37:15.000Z",
        "tweet_content": "My car loan is running in HDFC Bank , I have to apply for the Extention of another 3 months EMI Moratorium for my loan, Where can i get that link, Kindly acknowledge. #hdfcbank    #hdfcloan    #hdfccarloan   #arvindkejariwal   #PMModi   #hdfclife   #hdfcloansupport",
        "replies": "2",
        "retweets": "",
        "likes": "",
        "app": "hdfc"
    },
    {
        "search_link": "https://twitter.com/search?q=%23hdfcloan&src=typed_query&f=top",
        "user_name": "Isparrow Services Pvt Ltd",
        "user_handle": "/isparrowhrsol",
        "tweet_date": "Aug 4, 2021",
        "timestamp": "2021-08-04T06:04:25.000Z",
        "tweet_content": "We  #isparrowhr  again come back with  #MEGA   #drive  for   #HDFCLoan    #FSA   #SalesOfficer   #hiring   #interview  at  #ahmedabad .\nFor more info call us at 9327632073 or email at jobs.isparrow03@gmail.com\nLet's start your  #jobs  on 5th August   #isparrowhrsolution   #isparrowhr   #gujarat   #india",
        "replies": "",
        "retweets": "1",
        "likes": "",
        "app": "hdfc"
    },
    {
        "search_link": "https://twitter.com/search?q=%23hdfcloan&src=typed_query&f=top",
        "user_name": "Lokesh Pande",
        "user_handle": "/lokeshp25",
        "tweet_date": "Sep 23, 2020",
        "timestamp": "2020-09-23T06:50:01.000Z",
        "tweet_content": "This is ur arrangement for Loan a/c holders in times of pandemic? Can't u just make an online process for this?\n\n #HDFCInCovid \n\nAddress: B-44-45, Galaxy Park, Sector-62, Noida, UP\n\n #hdfc    #hdfcloan    #Covid_19   #SocialDistancing \n \n    ",
        "replies": "1",
        "retweets": "1",
        "likes": "",
        "app": "hdfc"
    },
    {
        "search_link": "https://twitter.com/search?q=%23hdfcloan&src=typed_query&f=top",
        "user_name": "Levonor",
        "user_handle": "/LevonorHyd",
        "tweet_date": "Jan 10, 2020",
        "timestamp": "2020-01-10T03:30:01.000Z",
        "tweet_content": "HDFC slashes home loan rate by 0.05 percent.     #homeloan    #hdfcloan    #gatedcommunity   #luxuryhomes   #luxuryhome   #luxuryrealestate   #luxurylife   #luxuryliving",
        "replies": "",
        "retweets": "",
        "likes": "1",
        "app": "hdfc"
    },
    {
        "search_link": "https://twitter.com/search?q=%23hdfcloan&src=typed_query&f=top",
        "user_name": "Swapnil Tendulkar",
        "user_handle": "/swappy146",
        "tweet_date": "Oct 12, 2021",
        "timestamp": "2021-10-12T12:42:59.000Z",
        "tweet_content": "#hdfcbank    #hdfcloan   what is use of taking pre approval loan . After applying online your people asking hard copy document.",
        "replies": "2",
        "retweets": "",
        "likes": "1",
        "app": "hdfc"
    },
    {
        "search_link": "https://twitter.com/search?q=%23hdfcloan&src=typed_query&f=top",
        "user_name": "Sudhanshu Dwivedi",
        "user_handle": "/sudhanshu19jan",
        "tweet_date": "May 20, 2021",
        "timestamp": "2021-05-20T05:10:13.000Z",
        "tweet_content": "#HDFCBank    #HDFCloan   Please understand we are common/middle class INDIAN people who always feel Pride/Relaxed/Happy ONLY when we \"Pay-Off\" all our dues. Seems you guys don't want us to feel in that way. \nWhy your processes is so complex, slow and stubborn.",
        "replies": "",
        "retweets": "",
        "likes": "",
        "app": "hdfc"
    },
    {
        "search_link": "https://twitter.com/search?q=%23hdfcloan&src=typed_query&f=top",
        "user_name": "Dipakk Dev",
        "user_handle": "/mrdipakdev",
        "tweet_date": "Sep 14, 2019",
        "timestamp": "2019-09-14T12:43:23.000Z",
        "tweet_content": "\nNever  #Refer  your friends for   #HDFCloan   \nI want to do Repayment of our Two Wheeler Loan. But at  #Rupnarayanpur    2 Wheeler Showroom\nYour Staff is Very Arrogant.  #HDFC  Staff have Misbehaved with Female Scooty owner.\nVery Disappointed ",
        "replies": "1",
        "retweets": "",
        "likes": "",
        "app": "hdfc"
    },
    {
        "search_link": "https://twitter.com/search?q=%23hdfcloan&src=typed_query&f=top",
        "user_name": "Rajni Devi",
        "user_handle": "/RAJNIDE32013336",
        "tweet_date": "May 9",
        "timestamp": "2023-05-09T01:35:23.000Z",
        "tweet_content": "Thanks CSC for providing this facilities at Rural areas  Car Loan Done Happy customer For loan Just visit our CSC center   #carloan    #hdfcloan    #loan   #carloan   #vehicleloan   #personalloan   #bikeloan   #agricultureloan   #hdfcbank",
        "replies": "",
        "retweets": "1",
        "likes": "4",
        "app": "hdfc"
    },
    {
        "search_link": "https://twitter.com/search?q=%23hdfcloan&src=typed_query&f=top",
        "user_name": "Rajni Devi",
        "user_handle": "/RAJNIDE32013336",
        "tweet_date": "Dec 17, 2022",
        "timestamp": "2022-12-17T07:30:59.000Z",
        "tweet_content": "Thanks CSC for providing this facilities at Rural areas \nTwo Wheeler Vehicle Loan Done Happy customer\nFor loan Just visit our CSC center\n\n #carloan    #hdfcloan    #loan   #carloan   #vehicleloan   #personalloan   #bikeloan   #agricultureloan   #hdfcbank",
        "replies": "2",
        "retweets": "2",
        "likes": "8",
        "app": "hdfc"
    },
    {
        "search_link": "https://twitter.com/search?q=%23hdfcloan&src=typed_query&f=top",
        "user_name": "Saurav Dabas",
        "user_handle": "/SauravDabas2",
        "tweet_date": "Jan 4",
        "timestamp": "2023-01-04T04:01:27.000Z",
        "tweet_content": "#HDFC  Ltd assigns loans worth  ₹8,892 cr in Q3     #hdfcloan",
        "replies": "",
        "retweets": "",
        "likes": "",
        "app": "hdfc"
    },
    {
        "search_link": "https://twitter.com/search?q=%23hdfcloan&src=typed_query&f=top",
        "user_name": "Ravish Uppal",
        "user_handle": "/UppalRavish",
        "tweet_date": "Sep 11, 2019",
        "timestamp": "2019-09-11T07:32:40.000Z",
        "tweet_content": "#hdfcloan  ,  #RBI  i have closed my acc 34285447 and acc 52450112. Still HDfC executive Himanshu Verma is harassing my relative Nitin Kumar calling from no 011 66519400/9500  #ministryoffinance ,  #hdfcbank ,  #hdfc .. Need justification for harassment on priority after cleaning all dues",
        "replies": "2",
        "retweets": "",
        "likes": "",
        "app": "hdfc"
    },
    {
        "search_link": "https://twitter.com/search?q=%23hdfcloan&src=typed_query&f=top",
        "user_name": "Amar Mishra",
        "user_handle": "/AmarMis06685539",
        "tweet_date": "May 8, 2021",
        "timestamp": "2021-05-08T02:35:00.000Z",
        "tweet_content": "#HDFCLIFE \n #hdfcbank \n  #hdfcloan  \n #rbigovernor \n\nFrom last 6 months hdfc team members are chitting with me. They are not resolving my problems and month n month they have been giving mentally harassment\n\nDear RBI team please help me to resolve my issue.  \n\nHdfc wrost bank",
        "replies": "1",
        "retweets": "1",
        "likes": "",
        "app": "hdfc"
    },
    {
        "search_link": "https://twitter.com/search?q=%23hdfcloan&src=typed_query&f=top",
        "user_name": "Minakshi Arora",
        "user_handle": "/7Minakshi",
        "tweet_date": "May 10, 2019",
        "timestamp": "2019-05-10T11:18:29.000Z",
        "tweet_content": "#hdfcloan   cheater bank, cheater representative pathetic service. They first cheated on rate of interest and now wasted my entire week.",
        "replies": "",
        "retweets": "",
        "likes": "",
        "app": "hdfc"
    },
    {
        "search_link": "https://twitter.com/search?q=%23hdfcloan&src=typed_query&f=top",
        "user_name": "Sudhanshu Dwivedi",
        "user_handle": "/sudhanshu19jan",
        "tweet_date": "May 19, 2021",
        "timestamp": "2021-05-19T14:11:32.000Z",
        "tweet_content": "HDFC Bank Loan department seems  have lost all concerns towards their customer. I have raised an issue 7-8 days back to their greivance cell but till now No revert..pathetic service.. highly disappointing and worrying... \n #hdfcbank    #HDFCloan    #HDFCgreivance   #RBI   #rbigovernor",
        "replies": "2",
        "retweets": "",
        "likes": "",
        "app": "hdfc"
    },
    {
        "search_link": "https://twitter.com/search?q=%23hdfcloan&src=typed_query&f=top",
        "user_name": "Princeraj",
        "user_handle": "/Princer88698378",
        "tweet_date": "Jun 6, 2020",
        "timestamp": "2020-06-06T10:33:02.000Z",
        "tweet_content": "Can any hdfc person help me on this?? I am not able to open this link since long & i have been told that i have to apply from here...already whatever lil amount i had in my account it has been deducted & its showing in - bal.\n\n #HDFC    #hdfcloan    #hdfckolkata   #HDFCLIFE   #hdfcbank",
        "replies": "2",
        "retweets": "",
        "likes": "",
        "app": "hdfc"
    },
    {
        "search_link": "https://twitter.com/search?q=%23hdfcloan&src=typed_query&f=top",
        "user_name": "vivek tiwari",
        "user_handle": "/vivekkmrtiwari",
        "tweet_date": "May 18, 2020",
        "timestamp": "2020-05-18T10:20:15.000Z",
        "tweet_content": "Dear   I got a call that my EMI is bounced because my account didn't have sufficient balance. Would like 2 tell u that isn't true, I have that much money in account. Not sure what went wrong with your system.   #HDFCLoan",
        "replies": "1",
        "retweets": "",
        "likes": "",
        "app": "hdfc"
    },
    {
        "search_link": "https://twitter.com/search?q=%23hdfcloan&src=typed_query&f=top",
        "user_name": "Subhendu Paul",
        "user_handle": "/SubhenduPaul24",
        "tweet_date": "Oct 11, 2018",
        "timestamp": "2018-10-10T19:28:14.000Z",
        "tweet_content": "#hdfcbank   #HDFC  worst bank process...  Even people don't know where to check cibil statement.. how such banks are operating...   #hdfcloan  ..",
        "replies": "",
        "retweets": "1",
        "likes": "",
        "app": "hdfc"
    },
    {
        "search_link": "https://twitter.com/search?q=%23hdfcloan&src=typed_query&f=top",
        "user_name": "Gourick Bhowmick",
        "user_handle": "/BhowmickGourick",
        "tweet_date": "Mar 22, 2019",
        "timestamp": "2019-03-22T05:36:14.000Z",
        "tweet_content": "#hdfc    #hdfcloan    #hdfcpersonalloan  I have applied for a personal loan and it’s been ten days with no updates. Good job hdfc. I get all the nuisance automated messages about holi and other forex related messages, but no update on my application for my personal loan.  #hdfcpathetic .",
        "replies": "1",
        "retweets": "",
        "likes": "",
        "app": "hdfc"
    },
    {
        "search_link": "https://twitter.com/search?q=%23hdfcloan&src=typed_query&f=top",
        "user_name": "Sanjay Kumar Mehta",
        "user_handle": "/sanjaymehta2013",
        "tweet_date": "Sep 26, 2022",
        "timestamp": "2022-09-26T14:17:18.000Z",
        "tweet_content": "Want a home loan for your dream home   Call us 9983001514\nOr Dm us  .offical  \n.\n.\n.\n #homeloan   #homeloans   #loaninindia   #india   #hdfcbank    #hdfcloan    #adani   #adanigroup   #loanagency   #emitra  ",
        "replies": "",
        "retweets": "",
        "likes": "",
        "app": "hdfc"
    },
    {
        "search_link": "https://twitter.com/search?q=%23hdfcloan&src=typed_query&f=top",
        "user_name": "Devarapaga Official™",
        "user_handle": "/devarapaga",
        "tweet_date": "Apr 7, 2020",
        "timestamp": "2020-04-07T15:48:01.000Z",
        "tweet_content": "   sir my creditcard bill debited from my account, so my balance _8,000/- showing after me taken   #hdfcloan   13,000/-  from EMI option so after sending return first debited my credicard bill so don't want to my loan amount 13k how to pay return ?  #hdfcbank",
        "replies": "",
        "retweets": "",
        "likes": "",
        "app": "hdfc"
    },
    {
        "search_link": "https://twitter.com/search?q=%23hdfcloan&src=typed_query&f=top",
        "user_name": "ASLI HEERA ",
        "user_handle": "/naushu7666",
        "tweet_date": "Oct 15, 2019",
        "timestamp": "2019-10-15T11:50:29.000Z",
        "tweet_content": "#hdfcbank  \njust to charge the panalty bank authority call after  the due date and reminds  that you have missed the EMI.this is very cheap  #hdb   #HDFC    #hdfcloan   ",
        "replies": "1",
        "retweets": "",
        "likes": "2",
        "app": "hdfc"
    },
    {
        "search_link": "https://twitter.com/search?q=%23hdfcloan&src=typed_query&f=top",
        "user_name": "Vignesh Natarajan",
        "user_handle": "/iamwki",
        "tweet_date": "Jun 18, 2021",
        "timestamp": "2021-06-18T04:21:05.000Z",
        "tweet_content": "Do  #banks  provide  #loans  for buying a new land or plot in india. If so any interest rates details and banks. Please suggest.  #hdfcbank   #sbibank   #axisbank    #hdfcloan    #sbiloan   #axisloan",
        "replies": "2",
        "retweets": "",
        "likes": "1",
        "app": "hdfc"
    },
    {
        "search_link": "https://twitter.com/search?q=%23hdfcloan&src=typed_query&f=top",
        "user_name": "romesh Gupta",
        "user_handle": "/sweet_nippy_23",
        "tweet_date": "Jun 25, 2020",
        "timestamp": "2020-06-25T04:31:13.000Z",
        "tweet_content": "#hdfcbank    #hdfcloan    #RBI  \nHDFC bank is one of the worst service provider in banking sector, mailed 2 times regarding moratorium on my outgoing loans but no response!!\nIs this the way you provide services to your customers.  #hdfcbank",
        "replies": "1",
        "retweets": "1",
        "likes": "",
        "app": "hdfc"
    },
    {
        "search_link": "https://twitter.com/search?q=%23hdfcloan&src=typed_query&f=top",
        "user_name": "rajat",
        "user_handle": "/jaiswal_rajat",
        "tweet_date": "Aug 28, 2021",
        "timestamp": "2021-08-28T08:32:01.000Z",
        "tweet_content": "I had raised a request to   #hdfcloan   on 24th aug regarding to close my personal loan and they advised that the payment link will come after 48 hours, no link received till today. I had call to customer care several times and everytime representative will tell place a new request.",
        "replies": "1",
        "retweets": "",
        "likes": "",
        "app": "hdfc"
    },
    {
        "search_link": "https://twitter.com/search?q=%23hdfcloan&src=typed_query&f=top",
        "user_name": "Aakankshabulbul",
        "user_handle": "/aakankshabulbul",
        "tweet_date": "Mar 26, 2021",
        "timestamp": "2021-03-25T22:48:51.000Z",
        "tweet_content": "#HDFC    #hdfcloan   I have paid my emi on time then why are you deducting money unnesssarly from my account. My due date is 7th of every month very month I am paying it without fail. Then why are you deducting money from my account",
        "replies": "",
        "retweets": "",
        "likes": "",
        "app": "hdfc"
    },
    {
        "search_link": "https://twitter.com/search?q=%23hdfcloan&src=typed_query&f=top",
        "user_name": "Dr Chaitanya Gupta",
        "user_handle": "/DrChaitanyaGup1",
        "tweet_date": "Mar 18, 2020",
        "timestamp": "2020-03-18T12:00:56.000Z",
        "tweet_content": "then I got a cashback of 5469 rs then they said that 531rs deducted due to late EMI that is my fault but u give cashback after 2 month then whose fault is that\nShame  #hdfcbank    #hdfcloan    #HDFC   #reservebank   #banking",
        "replies": "2",
        "retweets": "1",
        "likes": "3",
        "app": "hdfc"
    },
    {
        "search_link": "https://twitter.com/search?q=%23hdfcloan&src=typed_query&f=top",
        "user_name": "GrowidePortfolio Management",
        "user_handle": "/GrowidePortfol1",
        "tweet_date": "Aug 28, 2019",
        "timestamp": "2019-08-28T11:24:30.000Z",
        "tweet_content": "#bajajloans   #paisabazar   #Mahindrafinance   #kotak  loans   #Hdfcloan  \nAre you getting problem to approved loans, here we provide you busines loans, home loans, Personal loans...\nNo document required.\nContact US-9004002948",
        "replies": "",
        "retweets": "",
        "likes": "",
        "app": "hdfc"
    },
    {
        "search_link": "https://twitter.com/search?q=%23hdfcloan&src=typed_query&f=top",
        "user_name": "Anmol Rawat",
        "user_handle": "/authoranmol",
        "tweet_date": "Apr 12, 2018",
        "timestamp": "2018-04-12T05:26:01.000Z",
        "tweet_content": "As a customer I am appalled at their behavior and would request everybody not to take  #loans  from   because they have no value for their old customers with perfect credit score.  #hdfcbank   #hdfcautoloan    #hdfcloan",
        "replies": "1",
        "retweets": "3",
        "likes": "3",
        "app": "hdfc"
    },
    {
        "search_link": "https://twitter.com/search?q=%23hdfcloan&src=typed_query&f=top",
        "user_name": "Gagan Sengar‌",
        "user_handle": "/gagansengar1",
        "tweet_date": "Apr 17, 2020",
        "timestamp": "2020-04-17T16:12:04.000Z",
        "tweet_content": "     Please debit myEmi From sbi Account   #hdfcloan    #emi   #ecs   #nach   #banking",
        "replies": "1",
        "retweets": "",
        "likes": "1",
        "app": "hdfc"
    },
    {
        "search_link": "https://twitter.com/search?q=%23hdfcloan&src=typed_query&f=top",
        "user_name": "Vineet Pandey",
        "user_handle": "/profvineetpande",
        "tweet_date": "Aug 11",
        "timestamp": "2023-08-11T04:45:34.000Z",
        "tweet_content": "I missed my due loan payment in hdfc bank and they are not providing any link to pay in fact they are not even responding. Didn’t know I have made a mistake by going to HDFC  #hdfc   #HDFCBANK    #hdfcloan",
        "replies": "1",
        "retweets": "1",
        "likes": "",
        "app": "hdfc"
    },
    {
        "search_link": "https://twitter.com/search?q=%23hdfcloan&src=typed_query&f=top",
        "user_name": "Afinoz Digitalizing Finance",
        "user_handle": "/AfinozIndia",
        "tweet_date": "May 11, 2021",
        "timestamp": "2021-05-11T09:52:19.000Z",
        "tweet_content": "Have multiple obligations? But unable to arrange funds? Then, fulfil your diverse array of personal expenditures with HDFC instant personal loan! \nApply Today   \n  #hdfcloan    #hdfcbank   #instantloan   #personalloan   #loan   #loanservices   #PersonalLoanBank   #Afinoz",
        "replies": "",
        "retweets": "",
        "likes": "",
        "app": "hdfc"
    },
    {
        "search_link": "https://twitter.com/search?q=%23hdfcloan&src=typed_query&f=top",
        "user_name": "rajinder singh",
        "user_handle": "/rajinder_virdi",
        "tweet_date": "Feb 6, 2020",
        "timestamp": "2020-02-06T14:58:15.000Z",
        "tweet_content": "#hdfcloan  \n #deepakparekh \n #kikimistry \nNo response to complaint sent..more than 24 hours..no acknowledgement..Sales greed at high...Loan ready to disburse but greed to sell insurance..Will take this to RBI /IRDAI if not resolved amicably..",
        "replies": "1",
        "retweets": "1",
        "likes": "",
        "app": "hdfc"
    },
    {
        "search_link": "https://twitter.com/search?q=%23hdfcloan&src=typed_query&f=top",
        "user_name": "Pankaj singla",
        "user_handle": "/Pankajs2685",
        "tweet_date": "May 10, 2019",
        "timestamp": "2019-05-10T06:13:04.000Z",
        "tweet_content": "#hdfcbank   #hdfccreditcard    #hdfcloan  \n #ConsumerAssembly   #fraud   #RBI   #complaint  \n\nYou people are not able to send me the bank statement till now where you said on Twitter to solve my issue on priority. Another month charges on my both accounts and brought my saving account -ve",
        "replies": "1",
        "retweets": "",
        "likes": "",
        "app": "hdfc"
    },
    {
        "search_link": "https://twitter.com/search?q=%23hdfcloan&src=typed_query&f=top",
        "user_name": "VikAsh",
        "user_handle": "/vikas___h",
        "tweet_date": "Mar 19",
        "timestamp": "2023-03-19T16:17:50.000Z",
        "tweet_content": "Dear  ,\n\nyou've been calling me everyday to ask if I need a loan even after telling you not to call me again.\nI understood you won't stop calling me.\n\nCan you call me everyday at 7am? So I can at least use your call as an alarm. #HDFCBank    #hdfcloan",
        "replies": "1",
        "retweets": "3",
        "likes": "",
        "app": "hdfc"
    },
    {
        "search_link": "https://twitter.com/search?q=%23hdfcloan&src=typed_query&f=top",
        "user_name": "Deepak",
        "user_handle": "/manutdeepak",
        "tweet_date": "Sep 9, 2016",
        "timestamp": "2016-09-09T12:39:54.000Z",
        "tweet_content": "thedesistuff's photo     #Hdfcloan   for  #Coldplay  tickets.",
        "replies": "",
        "retweets": "",
        "likes": "",
        "app": "hdfc"
    },
    {
        "search_link": "https://twitter.com/search?q=%23hdfcloan&src=typed_query&f=top",
        "user_name": "Bookmypersonalloan",
        "user_handle": "/bookmypersonals",
        "tweet_date": "Aug 19, 2019",
        "timestamp": "2019-08-19T10:49:58.000Z",
        "tweet_content": "Are You looking for Personal loan ? These are the things you must know before taking personal loan any where..,\n\n #homeloans   #eligibility   #personalloans   #businessloans   #carloans   #lowcibil   #bookmypersonalloan    #hdfcloan    #iciciloan   #citybankloan   #indusindloan",
        "replies": "",
        "retweets": "",
        "likes": "1",
        "app": "hdfc"
    },
    {
        "search_link": "https://twitter.com/search?q=%23hdfcloan&src=typed_query&f=top",
        "user_name": "Natasha Gupta",
        "user_handle": "/guptanatasha",
        "tweet_date": "Sep 29, 2022",
        "timestamp": "2022-09-29T09:18:28.000Z",
        "tweet_content": "#hdfcloan   department worst customer service. they dont send NOC & then harass customers making senior citizens wait for 3 hours. never take a loan from them worst service   ",
        "replies": "1",
        "retweets": "",
        "likes": "",
        "app": "hdfc"
    },
    {
        "search_link": "https://twitter.com/search?q=%23hdfcloan&src=typed_query&f=top",
        "user_name": "Joydeep Sarkar",
        "user_handle": "/jd_cal5",
        "tweet_date": "Dec 8, 2021",
        "timestamp": "2021-12-08T09:13:42.000Z",
        "tweet_content": "For West Bengal STUDENTS' CREDIT CARD even  #hdfcbank   is asking for detailed Financial Particulars as MANDATE of Guardian as Co-applicant; then how the State Government is the Guarantor for this project.  #Westbengal   #education   #studentscreditcard   #CMO   #nabanna    #hdfcloan    #loans",
        "replies": "",
        "retweets": "",
        "likes": "2",
        "app": "hdfc"
    },
    {
        "search_link": "https://twitter.com/search?q=%23hdfcloan&src=typed_query&f=top",
        "user_name": "Ceshant Krishna Ganjoo",
        "user_handle": "/CeshantGanjoo",
        "tweet_date": "May 23",
        "timestamp": "2023-05-23T08:05:29.000Z",
        "tweet_content": "Having issue with hdfc CD loan and no help is being provided by anyone. Even after paying all the dues they are still charging amounts and calling 10 times in a day to clear dues coming from no where. Nothing can be tracked online as well. \n\n #hdfc   #hdfcbank    #hdfcloan",
        "replies": "1",
        "retweets": "3",
        "likes": "",
        "app": "hdfc"
    },
    {
        "search_link": "https://twitter.com/search?q=%23hdfcloan&src=typed_query&f=top",
        "user_name": "ET Auto",
        "user_handle": "/ETAuto",
        "tweet_date": "Jul 24, 2020",
        "timestamp": "2020-07-24T03:30:11.000Z",
        "tweet_content": "ETAuto | RBI seeks internal car loan investigation details from HDFC bank  #HDFC   #HdfcBank    #HDFCLoan    #CarLoansHdfc   #TheReserveBankOfIndia   #RBI   #HdfcCarLoans",
        "replies": "",
        "retweets": "",
        "likes": "3",
        "app": "hdfc"
    },
    {
        "search_link": "https://twitter.com/search?q=%23hdfcloan&src=typed_query&f=top",
        "user_name": "TechCircle",
        "user_handle": "/TechCircleIndia",
        "tweet_date": "Jul 5, 2022",
        "timestamp": "2022-07-05T09:10:28.000Z",
        "tweet_content": "HDFC simplifies its customer lending with Salesforce \n \n #HDFC   #CustomerLending   #Salesforce    #HdfcLoan",
        "replies": "",
        "retweets": "",
        "likes": "",
        "app": "hdfc"
    },
    {
        "search_link": "https://twitter.com/search?q=%23hdfcloan&src=typed_query&f=top",
        "user_name": "surela ganguly",
        "user_handle": "/surela2912",
        "tweet_date": "Feb 15",
        "timestamp": "2023-02-15T06:52:32.000Z",
        "tweet_content": "Here is the screen shots where many has given notes of her language, why   #hdfcloan   you don't terminate this type of employee? This is not IVR call as the same number calling repeatedly, she told I will call n number times.",
        "replies": "",
        "retweets": "",
        "likes": "",
        "app": "hdfc"
    },
    {
        "search_link": "https://twitter.com/search?q=%23hdfcloan&src=typed_query&f=top",
        "user_name": "CSCeGov",
        "user_handle": "/CSCegov_",
        "tweet_date": "Jun 8, 2021",
        "timestamp": "2021-06-08T03:00:00.000Z",
        "tweet_content": "Launch of INSTANT CONSUMER FINANCE...\n\nEMI On the Go @CSC...\n\nWatch it LIVE on the  #CSC  Facebook Page, 8th June 2021(Today), at 10 AM.\n\n #DigitalIndia   #TransformingIndia   #HDFCBank    #HDFCLoan    #TuesdayMotivation   #tuesdayvibe",
        "replies": "3",
        "retweets": "16",
        "likes": "87",
        "app": "hdfc"
    },
    {
        "search_link": "https://twitter.com/search?q=%23hdfcloan&src=typed_query&f=top",
        "user_name": "ABN Telugu",
        "user_handle": "/abntelugutv",
        "tweet_date": "Jun 26, 2021",
        "timestamp": "2021-06-26T10:58:32.000Z",
        "tweet_content": "HDFC లోన్ అకౌంట్ లోకి ఆ డబ్బులు వెనక్కి | HDFC Bank to Refund GPS Device Commission | ABN 3 Mins\n #HDFC    #HDFCLoan    #ABN \nWatch Video: ",
        "replies": "",
        "retweets": "",
        "likes": "1",
        "app": "hdfc"
    },
    {
        "search_link": "https://twitter.com/search?q=%23hdfcloan&src=typed_query&f=top",
        "user_name": "Business Standard",
        "user_handle": "/bsindia",
        "tweet_date": "Aug 2, 2021",
        "timestamp": "2021-08-02T07:40:00.000Z",
        "tweet_content": "Company says said the profit numbers for Q1Fy22 are comparable with that of the previous year for reasons including higher effective tax rate\n\nAbhijit Lele reports \n\n  #HDFCLoan    #HDFC   #HomeLoans",
        "replies": "",
        "retweets": "1",
        "likes": "8",
        "app": "hdfc"
    },
    {
        "search_link": "https://twitter.com/search?q=%23hdfcloan&src=typed_query&f=top",
        "user_name": "The Telegraph",
        "user_handle": "/ttindia",
        "tweet_date": "Jun 7, 2022",
        "timestamp": "2022-06-07T11:23:00.000Z",
        "tweet_content": " increased its Marginal Cost of funding based Lending Rate by 0.35 per cent from June 7. Learn about their new loan plans here: \n\n \n #banking   #hdfc   #BusinessNews   #HDFC    #HDFCloan    #loanscheme   #lendingrate   #indianbanks",
        "replies": "",
        "retweets": "",
        "likes": "1",
        "app": "hdfc"
    }
]